LICENSE
MANIFEST.in
README.md
setup.cfg
setup.py
django_roi_buro_sample_project.egg-info/PKG-INFO
django_roi_buro_sample_project.egg-info/SOURCES.txt
django_roi_buro_sample_project.egg-info/dependency_links.txt
django_roi_buro_sample_project.egg-info/requires.txt
django_roi_buro_sample_project.egg-info/top_level.txt
roiburo/__init__.py
roiburo/asgi.py
roiburo/manage.py
roiburo/middlewares.py
roiburo/models.py
roiburo/settings.py
roiburo/tests.py
roiburo/urls.py
roiburo/wsgi.py
roiburo/client/__init__.py
roiburo/client/main.py
roiburo/core/__init__.py
roiburo/core/apps.py
roiburo/core/models.py
roiburo/core/serializers.py
roiburo/core/services.py
roiburo/core/tests.py
roiburo/core/urls.py
roiburo/core/views.py
roiburo/core/migrations/0001_initial.py
roiburo/core/migrations/__init__.py