Metadata-Version: 2.1
Name: django-roi-buro-sample-project
Version: 0.1.9
Summary: A Django app to save cpu usage and view stats.
Home-page: https://gitlab.com/iplatforms_/roi-buro-test-project
Author: Alexey Vasilenko
Author-email: avavasilenko@gmail.com
License: BSD
Platform: UNKNOWN
Classifier: Environment :: Web Environment
Classifier: Framework :: Django
Classifier: Framework :: Django :: 3.2
Classifier: Intended Audience :: Developers
Classifier: License :: OSI Approved :: BSD License
Classifier: Operating System :: OS Independent
Classifier: Programming Language :: Python
Classifier: Programming Language :: Python :: 3
Classifier: Programming Language :: Python :: 3 :: Only
Classifier: Programming Language :: Python :: 3.6
Classifier: Programming Language :: Python :: 3.7
Classifier: Programming Language :: Python :: 3.8
Classifier: Programming Language :: Python :: 3.9
Classifier: Topic :: Internet :: WWW/HTTP
Requires-Python: >=3.6
License-File: LICENSE
